requests_unifi_auth/__init__.py
requests_unifi_auth/auth.py
requests_unifi_auth-0.1.4.dist-info/licenses/LICENSE
requests_unifi_auth-0.1.4.dist-info/METADATA
requests_unifi_auth-0.1.4.dist-info/WHEEL
requests_unifi_auth-0.1.4.dist-info/top_level.txt
requests_unifi_auth-0.1.4.dist-info/RECORD
