Metadata-Version: 2.4
Name: requests-unifi-auth
Version: 0.1.4
Summary: Ubiquiti Unifi Controller API authorization class for python requests library. Takes care of authentification and CSRF handling.
Author-email: Roman Akinfeev <akinfold@gmail.com>
License: MIT
Project-URL: Homepage, https://github.com/akinfold/requests-unifi-auth
Project-URL: Source, https://github.com/akinfold/requests-unifi-auth
Keywords: unifi,ubiquiti,api,networking,controller,requests
Classifier: Programming Language :: Python :: 3
Classifier: License :: OSI Approved :: MIT License
Classifier: Operating System :: OS Independent
Requires-Python: >=3.8
License-File: LICENSE
Requires-Dist: requests>=2.25
Provides-Extra: test
Requires-Dist: pytest>=7.0.0; extra == "test"
Requires-Dist: pytest-cov>=4.0.0; extra == "test"
Dynamic: license-file
